{
    "app_info": {
        "version": "1.3.0",
        "release_date": "2025-07-29",
        "package_name": "BBH3ScanLaunch_Setup_v1.3.0.exe",
        "changelog_path": "updates/changelog.txt",
        "size": "79MB"
    },
    "oa_info": {
        "oa_token": "e257aaa274fb2239094cbe64d9f5ee3e",
        "bh_ver": "8.4.0"
    },
    "sources": {
        "download_url": {
            "yoursources1": "https://url/BBH3ScanLaunch_Setup_vx.x.x.exe",
            "yoursources2": "https://url/BBH3ScanLaunch_Setup_vx.x.x.exe"
        },
        "changelog": {
            "yoursources1": "https://url/changelog.txt",
            "yoursources2": "https://url/changelog.txt"
        }
    }
}